gtnash/__init__.py
gtnash/game/__init__.py
gtnash/game/abstractgame.py
gtnash/game/bayesian_hypergraphicalgame.py
gtnash/game/bayesiangame.py
gtnash/game/graphicalgame.py
gtnash/game/hypergraphicalgame.py
gtnash/game/normalformgame.py
gtnash/game/polymatrixgame.py
gtnash/solver/__init__.py
gtnash/solver/lemkehowson_polymatrix.py
gtnash/solver/pns.py
gtnash/solver/wilsonalgorithm.py
gtnash/util/__init__.py
gtnash/util/irda.py
gtnash/util/polynomial_complementary_problem.py
gtnash-1.0.0.dist-info/METADATA
gtnash-1.0.0.dist-info/WHEEL
gtnash-1.0.0.dist-info/top_level.txt
gtnash-1.0.0.dist-info/RECORD
