Metadata-Version: 2.1
Name: gtnash
Version: 1.0.0
Summary: Python Nash Equilibrium Computation Utilities
Home-page: https://forgemia.inra.fr/game-theory-tools-group/gtnash/
Author: Régis Sabbadin
Author-email: regis.sabbadin@inrae.fr
